inter_morse/__init__.py
inter_morse/__main__.py
inter_morse-1.0.2.dist-info/LICENSE.txt
inter_morse-1.0.2.dist-info/METADATA
inter_morse-1.0.2.dist-info/WHEEL
inter_morse-1.0.2.dist-info/entry_points.txt
inter_morse-1.0.2.dist-info/top_level.txt
inter_morse-1.0.2.dist-info/RECORD
