Metadata-Version: 2.1
Name: inter-morse
Version: 1.0.2
Summary: Interpret wav audio files to Morse code and translate it.
Home-page: https://github.com/cnyllou/inter-morse
Author: Cnyllou
Author-email: cnyllou@gmail.com
License: GPLv3
Project-URL: Source, https://github.com/cnyllou/inter-morse/
Project-URL: Tracker, https://github.com/cnyllou/inter-morse/issues
Platform: UNKNOWN
Classifier: License :: OSI Approved :: GNU General Public License v3 or later (GPLv3+)
Classifier: Programming Language :: Python :: 3
Classifier: Programming Language :: Python :: 3.9
Classifier: Programming Language :: Python :: 3.10
Requires-Dist: pydub
Requires-Dist: matplotlib
